<Service xsi:noNamespaceSchemaLocation="http://schemas.bluetooth.org/Documents/service.xsd"
         xmlns:xsi="http://www.w3.org/2001/XMLSchema-instance" name="Soma Blinds"
         type="org.bluetooth.service.somablind" uuid="1861" last-modified="2018-09-06">
<InformativeText>
    <Abstract>
        Soma Blinds control
    </Abstract>
    <Summary>
        Controller for Soma Blinds
    </Summary>
</InformativeText>
<Dependencies>
    <Dependency>This service has no dependencies on other GATT-based services.</Dependency>
</Dependencies>
<GATTRequirements>
    <Requirement subProcedure="Write Characteristic Value">Mandatory</Requirement>
    <Requirement subProcedure="Notification">Mandatory</Requirement>
    <Requirement subProcedure="Read Characteristic Descriptors">Mandatory</Requirement>
    <Requirement subProcedure="Write Characteristic Descriptors">Mandatory</Requirement>
</GATTRequirements>
<Transports>
    <Classic>false</Classic>
    <LowEnergy>true</LowEnergy>
</Transports>
<ErrorCodes>
</ErrorCodes>
<Characteristics>
    <Characteristic name="Soma Blinds"
                    type="org.bluetooth.characteristic.somablind">
        <InformativeText>Blind control</InformativeText>
        <Requirement>Mandatory</Requirement>
        <Properties>
            <Read>Excluded</Read>
            <Write>Excluded</Write>
            <WriteWithoutResponse>Excluded</WriteWithoutResponse>
            <SignedWrite>Excluded</SignedWrite>
            <ReliableWrite>Excluded</ReliableWrite>
            <Notify>Excluded</Notify>
            <Indicate>Mandatory</Indicate>
            <WritableAuxiliaries>Excluded</WritableAuxiliaries>
            <Broadcast>Excluded</Broadcast>
        </Properties>
    </Characteristic>
</Characteristics>
</Service>
